guide/__init__.py
guide/base.py
guide/tools.py
guide/util.py
guide/tests/__init__.py
guide/tests/simple_tests.py
guide-0.0.8.dist-info/LICENSE
guide-0.0.8.dist-info/METADATA
guide-0.0.8.dist-info/WHEEL
guide-0.0.8.dist-info/top_level.txt
guide-0.0.8.dist-info/RECORD
