Metadata-Version: 2.1
Name: guide
Version: 0.0.8
Summary: Simple object to navigate complex python objects
Home-page: https://github.com/thorwhalen/guide
Author: Thor Whalen
License: apache-2.0
Platform: any
Requires-Dist: dol
Requires-Dist: i2
